hogwarts_terminal-0.2.dist-info/licenses/LICENSE
spells/__init__.py
spells/spell.py
hogwarts_terminal-0.2.dist-info/METADATA
hogwarts_terminal-0.2.dist-info/WHEEL
hogwarts_terminal-0.2.dist-info/entry_points.txt
hogwarts_terminal-0.2.dist-info/top_level.txt
hogwarts_terminal-0.2.dist-info/RECORD
