Metadata-Version: 2.4
Name: hogwarts-terminal
Version: 0.2
Summary: Harry Potter-themed Magical Linux/Windows terminal commands
Author: Ranjana M Suvarna
License-File: LICENSE
Requires-Dist: colorama
Dynamic: author
Dynamic: description
Dynamic: description-content-type
Dynamic: license-file
Dynamic: requires-dist
Dynamic: summary
